{"nodes": [{"id": "test_integration", "label": "integration.test.tsx \u2014 full game integration tests", "file_type": "code", "source_file": "/Users/neilsupratikbaksi/Documents/Website/wordle/src/__tests__/integration.test.tsx", "source_location": null, "source_url": null, "captured_at": null, "author": null, "contributor": null}, {"id": "invariant_board_always_6_rows", "label": "Invariant: board always renders exactly 6 rows", "file_type": "code", "source_file": "/Users/neilsupratikbaksi/Documents/Website/wordle/src/__tests__/integration.test.tsx", "source_location": "line 164", "source_url": null, "captured_at": null, "author": null, "contributor": null}], "edges": [{"source": "test_integration", "target": "invariant_board_always_6_rows", "relation": "verifies", "confidence": "EXTRACTED", "confidence_score": 1.0, "source_file": "/Users/neilsupratikbaksi/Documents/Website/wordle/src/__tests__/integration.test.tsx", "source_location": "line 164", "weight": 1.0}], "hyperedges": []}